pypidoctor/__init__.py
pypidoctor/build.py
pypidoctor/query.py
pypidoctor/utils.py
pypidoctor/queryengine/__init__.py
pypidoctor/queryengine/factory.py
pypidoctor/queryengine/querys.py
pypidoctor/reader/__init__.py
pypidoctor/reader/factory.py
pypidoctor/reader/reader.py
pypidoctor-0.1.3.dist-info/METADATA
pypidoctor-0.1.3.dist-info/WHEEL
pypidoctor-0.1.3.dist-info/top_level.txt
pypidoctor-0.1.3.dist-info/RECORD
