Metadata-Version: 2.4
Name: pypidoctor
Version: 0.1.3
Summary: 模型query理解能力
Requires-Python: >=3.10
Requires-Dist: black>=25.1.0
Requires-Dist: toolsz>=0.1.4
